source_google_search_console/__init__.py
source_google_search_console/components.py
source_google_search_console/config_migrations.py
source_google_search_console/exceptions.py
source_google_search_console/manifest.yaml
source_google_search_console/run.py
source_google_search_console/service_account_authenticator.py
source_google_search_console/source.py
source_google_search_console/spec.json
airbyte_source_google_search_console-1.9.4.dist-info/METADATA
airbyte_source_google_search_console-1.9.4.dist-info/WHEEL
airbyte_source_google_search_console-1.9.4.dist-info/entry_points.txt
airbyte_source_google_search_console-1.9.4.dist-info/RECORD
