Metadata-Version: 2.3
Name: airbyte-source-google-search-console
Version: 1.9.4
Summary: Source implementation for Google Search Console.
License: Elv2
Author: Airbyte
Author-email: contact@airbyte.io
Requires-Python: >=3.10,<3.12
Classifier: License :: Other/Proprietary License
Classifier: Programming Language :: Python :: 3
Classifier: Programming Language :: Python :: 3.10
Classifier: Programming Language :: Python :: 3.11
Requires-Dist: airbyte-cdk (>=6,<7)
Requires-Dist: google-api-python-client (==2.105.0)
Requires-Dist: google-auth (==2.23.3)
Requires-Dist: pendulum (>=3.1.0,<4.0.0)
Project-URL: Documentation, https://docs.airbyte.com/integrations/sources/google-search-console
Project-URL: Homepage, https://airbyte.com
Project-URL: Repository, https://github.com/airbytehq/airbyte
